pycsoap/__init__.py
pycsoap/base.py
pycsoap/core.py
pycsoap/descriptors.py
pycsoap/genBasis.py
pycsoap/getBasis.py
pycsoap/msg.py
pycsoap/soaplite.py
pycsoap/system.py
pycsoap-0.1.2.dist-info/DESCRIPTION.rst
pycsoap-0.1.2.dist-info/METADATA
pycsoap-0.1.2.dist-info/RECORD
pycsoap-0.1.2.dist-info/WHEEL
pycsoap-0.1.2.dist-info/metadata.json
pycsoap-0.1.2.dist-info/top_level.txt
src/libsoapGTO.so
src/libsoapGeneral.so
src/libsoapPySig.so
