Metadata-Version: 1.1
Name: pycsoap
Version: 0.1.2
Summary: Generation of SOAP descriptors.
Home-page: https://gitlab.com/andrewhuynguyen/pycsoap
Author: Andrew H Nguyen
Author-email: andrewhuynguyen10@gmail.com
License: BSD 3-clause New or Revised License
Platform: UNKNOWN
Classifier: Development Status :: 3 - Alpha
Classifier: Intended Audience :: Science/Research
Classifier: Intended Audience :: Developers
Classifier: Natural Language :: English
Classifier: License :: OSI Approved :: BSD License
Classifier: Operating System :: MacOS
Classifier: Operating System :: POSIX :: Linux
Classifier: Programming Language :: Python
Classifier: Programming Language :: Python :: 2
Classifier: Programming Language :: Python :: 2.7
Classifier: Programming Language :: Python :: 3
Classifier: Programming Language :: Python :: 3.5
Classifier: Programming Language :: C
Classifier: Topic :: Scientific/Engineering
